dmi_open_data/__init__.py
dmi_open_data/client.py
dmi_open_data/enums.py
dmi_open_data/utils.py
dmi_open_data_pandas-0.1.dist-info/METADATA
dmi_open_data_pandas-0.1.dist-info/WHEEL
dmi_open_data_pandas-0.1.dist-info/licenses/LICENSE
dmi_open_data_pandas-0.1.dist-info/RECORD
