Metadata-Version: 2.3
Name: dmi-open-data-pandas
Version: 0.1
Summary: A package to extract data from DMI Open Data into pandas dataframes
Project-URL: Homepage, https://github.com/edu230991/dmi-open-data
Project-URL: Issues, https://github.com/edu230991/dmi-open-data/issues
Author-email: Edoardo Simioni <edu230991@gmail.com>
License-File: LICENSE
Classifier: Operating System :: OS Independent
Classifier: Programming Language :: Python :: 3
Requires-Python: >=3.9
Requires-Dist: pandas<2.3,>=2.2
Requires-Dist: requests>=2.25.1
Requires-Dist: tenacity>=6.3.1
